external_dependencies/__init__.py
external_dependencies/cli.py
external_dependencies/utils.py
external_dependencies-1.1.0.dist-info/METADATA
external_dependencies-1.1.0.dist-info/WHEEL
external_dependencies-1.1.0.dist-info/entry_points.txt
external_dependencies-1.1.0.dist-info/RECORD
