Metadata-Version: 2.3
Name: external-dependencies
Version: 1.1.0
Summary: A CLI interface to install 'Requires-External' dependencies using apt or static build from s3
Requires-Python: <3.13,>=3.9
Requires-Dist: boto3
Requires-Dist: typer>=0.12.5
